{
  "0": [
    {
      "id": 0,
      "type": 0.4241446390255541,
      "size": 443,
      "loadReceiveTime": 0
    },
    {
      "id": 1,
      "type": 0.375541943619361,
      "size": 187,
      "loadReceiveTime": 0
    }
  ],
  "1": [
    {
      "id": 2,
      "type": 0.3436992128938203,
      "size": 910,
      "loadReceiveTime": 1
    },
    {
      "id": 3,
      "type": 0.5437151064418659,
      "size": 250,
      "loadReceiveTime": 1
    }
  ],
  "2": [
    {
      "id": 4,
      "type": 0.3620416650812981,
      "size": 1027,
      "loadReceiveTime": 2
    },
    {
      "id": 5,
      "type": 0.8216990146954088,
      "size": 491,
      "loadReceiveTime": 2
    }
  ],
  "3": [
    {
      "id": 6,
      "type": 0.39331941069329246,
      "size": 652,
      "loadReceiveTime": 3
    },
    {
      "id": 7,
      "type": 0.9350882540952825,
      "size": 313,
      "loadReceiveTime": 3
    }
  ],
  "4": [
    {
      "id": 8,
      "type": 0.7771727568371307,
      "size": 354,
      "loadReceiveTime": 4
    },
    {
      "id": 9,
      "type": 0.46899064571256854,
      "size": 66,
      "loadReceiveTime": 4
    }
  ],
  "5": [
    {
      "id": 10,
      "type": 0.6657770066732223,
      "size": 1829,
      "loadReceiveTime": 5
    },
    {
      "id": 11,
      "type": 0.9380950284146903,
      "size": 206,
      "loadReceiveTime": 5
    }
  ],
  "6": [
    {
      "id": 12,
      "type": 0.040154028398696084,
      "size": 525,
      "loadReceiveTime": 6
    },
    {
      "id": 13,
      "type": 0.5141385255665021,
      "size": 22,
      "loadReceiveTime": 6
    }
  ],
  "7": [
    {
      "id": 14,
      "type": 0.5360003816875498,
      "size": 86,
      "loadReceiveTime": 7
    },
    {
      "id": 15,
      "type": 0.09537078231387808,
      "size": 782,
      "loadReceiveTime": 7
    }
  ],
  "8": [
    {
      "id": 16,
      "type": 0.8566540164178209,
      "size": 775,
      "loadReceiveTime": 8
    },
    {
      "id": 17,
      "type": 0.4009337801862656,
      "size": 2604,
      "loadReceiveTime": 8
    }
  ],
  "9": [
    {
      "id": 18,
      "type": 0.11026517970579275,
      "size": 337,
      "loadReceiveTime": 9
    },
    {
      "id": 19,
      "type": 0.6995689440589969,
      "size": 45,
      "loadReceiveTime": 9
    }
  ],
  "10": [
    {
      "id": 20,
      "type": 0.28014887698188073,
      "size": 592,
      "loadReceiveTime": 10
    },
    {
      "id": 21,
      "type": 0.2609780043361285,
      "size": 178,
      "loadReceiveTime": 10
    }
  ],
  "11": [
    {
      "id": 22,
      "type": 0.14559974594063307,
      "size": 99,
      "loadReceiveTime": 11
    },
    {
      "id": 23,
      "type": 0.9128665626605081,
      "size": 52,
      "loadReceiveTime": 11
    }
  ],
  "12": [
    {
      "id": 24,
      "type": 0.3822129386432338,
      "size": 219,
      "loadReceiveTime": 12
    },
    {
      "id": 25,
      "type": 0.39000902433112405,
      "size": 1682,
      "loadReceiveTime": 12
    }
  ],
  "13": [
    {
      "id": 26,
      "type": 0.34633538435648825,
      "size": 1152,
      "loadReceiveTime": 13
    },
    {
      "id": 27,
      "type": 0.2443244863393894,
      "size": 213,
      "loadReceiveTime": 13
    }
  ],
  "14": [
    {
      "id": 28,
      "type": 0.026235342105827897,
      "size": 624,
      "loadReceiveTime": 14
    },
    {
      "id": 29,
      "type": 0.17099194090833447,
      "size": 579,
      "loadReceiveTime": 14
    }
  ],
  "15": [
    {
      "id": 30,
      "type": 0.11206833923094761,
      "size": 611,
      "loadReceiveTime": 15
    },
    {
      "id": 31,
      "type": 0.31812673506005407,
      "size": 228,
      "loadReceiveTime": 15
    }
  ],
  "16": [
    {
      "id": 32,
      "type": 0.37177843085534956,
      "size": 1477,
      "loadReceiveTime": 16
    },
    {
      "id": 33,
      "type": 0.487250714448342,
      "size": 126,
      "loadReceiveTime": 16
    }
  ],
  "17": [
    {
      "id": 34,
      "type": 0.5251071011262056,
      "size": 994,
      "loadReceiveTime": 17
    },
    {
      "id": 35,
      "type": 0.07478059245241186,
      "size": 743,
      "loadReceiveTime": 17
    }
  ],
  "18": [
    {
      "id": 36,
      "type": 0.12441359448406919,
      "size": 832,
      "loadReceiveTime": 18
    },
    {
      "id": 37,
      "type": 0.3992585134777884,
      "size": 380,
      "loadReceiveTime": 18
    }
  ],
  "19": [
    {
      "id": 38,
      "type": 0.029455869521339162,
      "size": 1215,
      "loadReceiveTime": 19
    },
    {
      "id": 39,
      "type": 0.11452783246643583,
      "size": 55,
      "loadReceiveTime": 19
    }
  ],
  "20": [
    {
      "id": 40,
      "type": 0.25440923063268484,
      "size": 128,
      "loadReceiveTime": 20
    },
    {
      "id": 41,
      "type": 0.09666434340164187,
      "size": 70,
      "loadReceiveTime": 20
    }
  ],
  "21": [
    {
      "id": 42,
      "type": 0.37239162717740015,
      "size": 1773,
      "loadReceiveTime": 21
    },
    {
      "id": 43,
      "type": 0.5342294267754797,
      "size": 2446,
      "loadReceiveTime": 21
    }
  ],
  "22": [
    {
      "id": 44,
      "type": 0.542835815051508,
      "size": 272,
      "loadReceiveTime": 22
    },
    {
      "id": 45,
      "type": 0.6959818986025454,
      "size": 537,
      "loadReceiveTime": 22
    }
  ],
  "23": [
    {
      "id": 46,
      "type": 0.11889618861965134,
      "size": 1241,
      "loadReceiveTime": 23
    },
    {
      "id": 47,
      "type": 0.981255625341146,
      "size": 192,
      "loadReceiveTime": 23
    }
  ],
  "24": [
    {
      "id": 48,
      "type": 0.44927506786005966,
      "size": 3390,
      "loadReceiveTime": 24
    },
    {
      "id": 49,
      "type": 0.13345393205738532,
      "size": 2452,
      "loadReceiveTime": 24
    }
  ],
  "25": [
    {
      "id": 50,
      "type": 0.027383467508652393,
      "size": 164,
      "loadReceiveTime": 25
    },
    {
      "id": 51,
      "type": 0.8305159653023877,
      "size": 54,
      "loadReceiveTime": 25
    }
  ],
  "26": [
    {
      "id": 52,
      "type": 0.8474866270422219,
      "size": 1521,
      "loadReceiveTime": 26
    },
    {
      "id": 53,
      "type": 0.09438845947357088,
      "size": 38,
      "loadReceiveTime": 26
    }
  ],
  "27": [
    {
      "id": 54,
      "type": 0.059643696557933445,
      "size": 1243,
      "loadReceiveTime": 27
    },
    {
      "id": 55,
      "type": 0.5196002294323419,
      "size": 200,
      "loadReceiveTime": 27
    }
  ],
  "28": [
    {
      "id": 56,
      "type": 0.2185469518680283,
      "size": 13,
      "loadReceiveTime": 28
    },
    {
      "id": 57,
      "type": 0.43862340148957846,
      "size": 708,
      "loadReceiveTime": 28
    }
  ],
  "29": [
    {
      "id": 58,
      "type": 0.3758687224031989,
      "size": 2811,
      "loadReceiveTime": 29
    },
    {
      "id": 59,
      "type": 0.4829904828668605,
      "size": 1664,
      "loadReceiveTime": 29
    }
  ],
  "30": [
    {
      "id": 60,
      "type": 0.26716916866193796,
      "size": 76,
      "loadReceiveTime": 30
    },
    {
      "id": 61,
      "type": 0.906376074230866,
      "size": 258,
      "loadReceiveTime": 30
    }
  ],
  "31": [
    {
      "id": 62,
      "type": 0.9664229293986248,
      "size": 659,
      "loadReceiveTime": 31
    },
    {
      "id": 63,
      "type": 0.8124316528517452,
      "size": 836,
      "loadReceiveTime": 31
    }
  ],
  "32": [
    {
      "id": 64,
      "type": 0.6611520873396739,
      "size": 13,
      "loadReceiveTime": 32
    },
    {
      "id": 65,
      "type": 0.045201268411959594,
      "size": 108,
      "loadReceiveTime": 32
    }
  ],
  "33": [
    {
      "id": 66,
      "type": 0.7378902071991702,
      "size": 984,
      "loadReceiveTime": 33
    },
    {
      "id": 67,
      "type": 0.3088580810857531,
      "size": 1130,
      "loadReceiveTime": 33
    }
  ],
  "34": [
    {
      "id": 68,
      "type": 0.5185668180945262,
      "size": 571,
      "loadReceiveTime": 34
    },
    {
      "id": 69,
      "type": 0.6614365598047642,
      "size": 178,
      "loadReceiveTime": 34
    }
  ],
  "35": [
    {
      "id": 70,
      "type": 0.39403462311966764,
      "size": 780,
      "loadReceiveTime": 35
    },
    {
      "id": 71,
      "type": 0.2758800023586918,
      "size": 80,
      "loadReceiveTime": 35
    }
  ],
  "36": [
    {
      "id": 72,
      "type": 0.14952137093147555,
      "size": 926,
      "loadReceiveTime": 36
    },
    {
      "id": 73,
      "type": 0.8966612015835176,
      "size": 901,
      "loadReceiveTime": 36
    }
  ],
  "37": [
    {
      "id": 74,
      "type": 0.9366224542470118,
      "size": 1755,
      "loadReceiveTime": 37
    },
    {
      "id": 75,
      "type": 0.48047914560471794,
      "size": 987,
      "loadReceiveTime": 37
    }
  ],
  "38": [
    {
      "id": 76,
      "type": 0.7567001448272044,
      "size": 341,
      "loadReceiveTime": 38
    },
    {
      "id": 77,
      "type": 0.7327431519699854,
      "size": 542,
      "loadReceiveTime": 38
    }
  ],
  "39": [
    {
      "id": 78,
      "type": 0.037961607314845214,
      "size": 436,
      "loadReceiveTime": 39
    },
    {
      "id": 79,
      "type": 0.3749908280948888,
      "size": 428,
      "loadReceiveTime": 39
    }
  ],
  "40": [
    {
      "id": 80,
      "type": 0.29329204566778166,
      "size": 537,
      "loadReceiveTime": 40
    },
    {
      "id": 81,
      "type": 0.37854874631018043,
      "size": 139,
      "loadReceiveTime": 40
    }
  ],
  "41": [
    {
      "id": 82,
      "type": 0.14834155053227094,
      "size": 2540,
      "loadReceiveTime": 41
    },
    {
      "id": 83,
      "type": 0.4991392540374695,
      "size": 1677,
      "loadReceiveTime": 41
    }
  ],
  "42": [
    {
      "id": 84,
      "type": 0.147834658168851,
      "size": 3923,
      "loadReceiveTime": 42
    },
    {
      "id": 85,
      "type": 0.3570774041592766,
      "size": 134,
      "loadReceiveTime": 42
    }
  ],
  "43": [
    {
      "id": 86,
      "type": 0.7630279803998927,
      "size": 173,
      "loadReceiveTime": 43
    },
    {
      "id": 87,
      "type": 0.11485393870233374,
      "size": 614,
      "loadReceiveTime": 43
    }
  ],
  "44": [
    {
      "id": 88,
      "type": 0.8475362651456262,
      "size": 1825,
      "loadReceiveTime": 44
    },
    {
      "id": 89,
      "type": 0.7535135039064971,
      "size": 577,
      "loadReceiveTime": 44
    }
  ],
  "45": [
    {
      "id": 90,
      "type": 0.8805689349248536,
      "size": 912,
      "loadReceiveTime": 45
    },
    {
      "id": 91,
      "type": 0.377116011961093,
      "size": 2248,
      "loadReceiveTime": 45
    }
  ],
  "46": [
    {
      "id": 92,
      "type": 0.03128573031802717,
      "size": 1678,
      "loadReceiveTime": 46
    },
    {
      "id": 93,
      "type": 0.29177810291464557,
      "size": 485,
      "loadReceiveTime": 46
    }
  ],
  "47": [
    {
      "id": 94,
      "type": 0.09145785759136338,
      "size": 311,
      "loadReceiveTime": 47
    },
    {
      "id": 95,
      "type": 0.40083804699516334,
      "size": 367,
      "loadReceiveTime": 47
    }
  ],
  "48": [
    {
      "id": 96,
      "type": 0.7563758597981003,
      "size": 230,
      "loadReceiveTime": 48
    },
    {
      "id": 97,
      "type": 0.33184313315172154,
      "size": 492,
      "loadReceiveTime": 48
    }
  ],
  "49": [
    {
      "id": 98,
      "type": 0.6793137102410081,
      "size": 486,
      "loadReceiveTime": 49
    },
    {
      "id": 99,
      "type": 0.2026071833625651,
      "size": 1013,
      "loadReceiveTime": 49
    }
  ],
  "50": [
    {
      "id": 100,
      "type": 0.6285715555875468,
      "size": 26,
      "loadReceiveTime": 50
    },
    {
      "id": 101,
      "type": 0.1656506423611166,
      "size": 1507,
      "loadReceiveTime": 50
    }
  ],
  "51": [
    {
      "id": 102,
      "type": 0.09699196893572548,
      "size": 310,
      "loadReceiveTime": 51
    },
    {
      "id": 103,
      "type": 0.7662655241954457,
      "size": 1515,
      "loadReceiveTime": 51
    }
  ],
  "52": [
    {
      "id": 104,
      "type": 0.5538118329971113,
      "size": 1809,
      "loadReceiveTime": 52
    },
    {
      "id": 105,
      "type": 0.37933610774159243,
      "size": 18,
      "loadReceiveTime": 52
    }
  ],
  "53": [
    {
      "id": 106,
      "type": 0.427005568944141,
      "size": 1351,
      "loadReceiveTime": 53
    },
    {
      "id": 107,
      "type": 0.5133750933083152,
      "size": 726,
      "loadReceiveTime": 53
    }
  ],
  "54": [
    {
      "id": 108,
      "type": 0.3165862876680787,
      "size": 4344,
      "loadReceiveTime": 54
    },
    {
      "id": 109,
      "type": 0.9351838008552187,
      "size": 2674,
      "loadReceiveTime": 54
    }
  ],
  "55": [
    {
      "id": 110,
      "type": 0.014131459845770244,
      "size": 2663,
      "loadReceiveTime": 55
    },
    {
      "id": 111,
      "type": 0.9935781166680548,
      "size": 1106,
      "loadReceiveTime": 55
    }
  ],
  "56": [
    {
      "id": 112,
      "type": 0.8766041499784745,
      "size": 559,
      "loadReceiveTime": 56
    },
    {
      "id": 113,
      "type": 0.12186490345833012,
      "size": 99,
      "loadReceiveTime": 56
    }
  ],
  "57": [
    {
      "id": 114,
      "type": 0.8174875950624299,
      "size": 278,
      "loadReceiveTime": 57
    },
    {
      "id": 115,
      "type": 0.08185396343650408,
      "size": 89,
      "loadReceiveTime": 57
    }
  ],
  "58": [
    {
      "id": 116,
      "type": 0.5323711268938831,
      "size": 606,
      "loadReceiveTime": 58
    },
    {
      "id": 117,
      "type": 0.8276170595711516,
      "size": 362,
      "loadReceiveTime": 58
    }
  ],
  "59": [
    {
      "id": 118,
      "type": 0.8633621807999063,
      "size": 1936,
      "loadReceiveTime": 59
    },
    {
      "id": 119,
      "type": 0.829817523679713,
      "size": 2196,
      "loadReceiveTime": 59
    }
  ],
  "60": [
    {
      "id": 120,
      "type": 0.3260660180227699,
      "size": 1787,
      "loadReceiveTime": 60
    },
    {
      "id": 121,
      "type": 0.823714497560853,
      "size": 754,
      "loadReceiveTime": 60
    }
  ],
  "61": [
    {
      "id": 122,
      "type": 0.4062390743959581,
      "size": 240,
      "loadReceiveTime": 61
    },
    {
      "id": 123,
      "type": 0.6894131747563685,
      "size": 32,
      "loadReceiveTime": 61
    }
  ],
  "62": [
    {
      "id": 124,
      "type": 0.504834930834045,
      "size": 742,
      "loadReceiveTime": 62
    },
    {
      "id": 125,
      "type": 0.774412881105704,
      "size": 386,
      "loadReceiveTime": 62
    }
  ],
  "63": [
    {
      "id": 126,
      "type": 0.05328447831011918,
      "size": 697,
      "loadReceiveTime": 63
    },
    {
      "id": 127,
      "type": 0.0036776185407279005,
      "size": 86,
      "loadReceiveTime": 63
    }
  ],
  "64": [
    {
      "id": 128,
      "type": 0.2648784066029215,
      "size": 311,
      "loadReceiveTime": 64
    },
    {
      "id": 129,
      "type": 0.6978176721550968,
      "size": 104,
      "loadReceiveTime": 64
    }
  ],
  "65": [
    {
      "id": 130,
      "type": 0.5910797857531649,
      "size": 330,
      "loadReceiveTime": 65
    },
    {
      "id": 131,
      "type": 0.8329066095303033,
      "size": 364,
      "loadReceiveTime": 65
    }
  ],
  "66": [
    {
      "id": 132,
      "type": 0.8124076013163484,
      "size": 1027,
      "loadReceiveTime": 66
    },
    {
      "id": 133,
      "type": 0.46493127385859556,
      "size": 800,
      "loadReceiveTime": 66
    }
  ],
  "67": [
    {
      "id": 134,
      "type": 0.3073952171344083,
      "size": 3,
      "loadReceiveTime": 67
    },
    {
      "id": 135,
      "type": 0.6138742453668429,
      "size": 1218,
      "loadReceiveTime": 67
    }
  ],
  "68": [
    {
      "id": 136,
      "type": 0.5995404045899662,
      "size": 1465,
      "loadReceiveTime": 68
    },
    {
      "id": 137,
      "type": 0.410197467995959,
      "size": 220,
      "loadReceiveTime": 68
    }
  ],
  "69": [
    {
      "id": 138,
      "type": 0.023313769206525725,
      "size": 655,
      "loadReceiveTime": 69
    },
    {
      "id": 139,
      "type": 0.44951058656393506,
      "size": 554,
      "loadReceiveTime": 69
    }
  ],
  "70": [
    {
      "id": 140,
      "type": 0.7949457427882136,
      "size": 251,
      "loadReceiveTime": 70
    },
    {
      "id": 141,
      "type": 0.16306080238546405,
      "size": 1468,
      "loadReceiveTime": 70
    }
  ],
  "71": [
    {
      "id": 142,
      "type": 0.7937804035827358,
      "size": 809,
      "loadReceiveTime": 71
    },
    {
      "id": 143,
      "type": 0.17690885275478774,
      "size": 2145,
      "loadReceiveTime": 71
    }
  ],
  "72": [
    {
      "id": 144,
      "type": 0.8517209155259569,
      "size": 2622,
      "loadReceiveTime": 72
    },
    {
      "id": 145,
      "type": 0.551510275596151,
      "size": 1800,
      "loadReceiveTime": 72
    }
  ],
  "73": [
    {
      "id": 146,
      "type": 0.007727243911108239,
      "size": 2734,
      "loadReceiveTime": 73
    },
    {
      "id": 147,
      "type": 0.5681278332470545,
      "size": 284,
      "loadReceiveTime": 73
    }
  ],
  "74": [
    {
      "id": 148,
      "type": 0.1009036604724931,
      "size": 4730,
      "loadReceiveTime": 74
    },
    {
      "id": 149,
      "type": 0.871282146463155,
      "size": 1029,
      "loadReceiveTime": 74
    }
  ],
  "76": [
    {
      "id": 150,
      "type": 0.6565556974627444,
      "size": 124,
      "loadReceiveTime": 76
    },
    {
      "id": 151,
      "type": 0.4165531504132802,
      "size": 1801,
      "loadReceiveTime": 76
    }
  ],
  "77": [
    {
      "id": 152,
      "type": 0.02089923503294666,
      "size": 3753,
      "loadReceiveTime": 77
    },
    {
      "id": 153,
      "type": 0.9569287823882922,
      "size": 708,
      "loadReceiveTime": 77
    }
  ],
  "78": [
    {
      "id": 154,
      "type": 0.7554444219509924,
      "size": 1165,
      "loadReceiveTime": 78
    },
    {
      "id": 155,
      "type": 0.42522737565017854,
      "size": 564,
      "loadReceiveTime": 78
    }
  ],
  "79": [
    {
      "id": 156,
      "type": 0.4377614838572763,
      "size": 4829,
      "loadReceiveTime": 79
    },
    {
      "id": 157,
      "type": 0.1686412890385729,
      "size": 2883,
      "loadReceiveTime": 79
    }
  ],
  "80": [
    {
      "id": 158,
      "type": 0.9769376554164895,
      "size": 2066,
      "loadReceiveTime": 80
    },
    {
      "id": 159,
      "type": 0.9132280639723982,
      "size": 196,
      "loadReceiveTime": 80
    }
  ],
  "81": [
    {
      "id": 160,
      "type": 0.5975001814263665,
      "size": 1629,
      "loadReceiveTime": 81
    },
    {
      "id": 161,
      "type": 0.6344681544996418,
      "size": 905,
      "loadReceiveTime": 81
    }
  ],
  "82": [
    {
      "id": 162,
      "type": 0.5728602847472859,
      "size": 1153,
      "loadReceiveTime": 82
    },
    {
      "id": 163,
      "type": 0.8635655847282386,
      "size": 493,
      "loadReceiveTime": 82
    }
  ],
  "83": [
    {
      "id": 164,
      "type": 0.8551438839627414,
      "size": 45,
      "loadReceiveTime": 83
    },
    {
      "id": 165,
      "type": 0.6475794901614678,
      "size": 11,
      "loadReceiveTime": 83
    }
  ],
  "84": [
    {
      "id": 166,
      "type": 0.5996988005178507,
      "size": 388,
      "loadReceiveTime": 84
    },
    {
      "id": 167,
      "type": 0.023608738430357157,
      "size": 2560,
      "loadReceiveTime": 84
    }
  ],
  "85": [
    {
      "id": 168,
      "type": 0.42487104552806043,
      "size": 1673,
      "loadReceiveTime": 85
    },
    {
      "id": 169,
      "type": 0.6277044758175931,
      "size": 23,
      "loadReceiveTime": 85
    }
  ],
  "86": [
    {
      "id": 170,
      "type": 0.9197411405322815,
      "size": 1156,
      "loadReceiveTime": 86
    },
    {
      "id": 171,
      "type": 0.0320895039311484,
      "size": 1065,
      "loadReceiveTime": 86
    }
  ],
  "87": [
    {
      "id": 172,
      "type": 0.6535943269222118,
      "size": 418,
      "loadReceiveTime": 87
    },
    {
      "id": 173,
      "type": 0.7855885061956263,
      "size": 530,
      "loadReceiveTime": 87
    }
  ],
  "88": [
    {
      "id": 174,
      "type": 0.9119166259735771,
      "size": 849,
      "loadReceiveTime": 88
    },
    {
      "id": 175,
      "type": 0.7675290463401503,
      "size": 479,
      "loadReceiveTime": 88
    }
  ],
  "89": [
    {
      "id": 176,
      "type": 0.16691360496379026,
      "size": 833,
      "loadReceiveTime": 89
    },
    {
      "id": 177,
      "type": 0.6302062257333945,
      "size": 627,
      "loadReceiveTime": 89
    }
  ],
  "90": [
    {
      "id": 178,
      "type": 0.1767735986654977,
      "size": 46,
      "loadReceiveTime": 90
    },
    {
      "id": 179,
      "type": 0.4005185372499718,
      "size": 345,
      "loadReceiveTime": 90
    }
  ],
  "91": [
    {
      "id": 180,
      "type": 0.6808147951605834,
      "size": 167,
      "loadReceiveTime": 91
    },
    {
      "id": 181,
      "type": 0.27659440704748217,
      "size": 2317,
      "loadReceiveTime": 91
    }
  ],
  "92": [
    {
      "id": 182,
      "type": 0.26065820282621566,
      "size": 2483,
      "loadReceiveTime": 92
    },
    {
      "id": 183,
      "type": 0.5449358361821006,
      "size": 1768,
      "loadReceiveTime": 92
    }
  ],
  "93": [
    {
      "id": 184,
      "type": 0.7603091562274054,
      "size": 2224,
      "loadReceiveTime": 93
    },
    {
      "id": 185,
      "type": 0.35601637093714955,
      "size": 461,
      "loadReceiveTime": 93
    }
  ],
  "94": [
    {
      "id": 186,
      "type": 0.4705052362886599,
      "size": 210,
      "loadReceiveTime": 94
    },
    {
      "id": 187,
      "type": 0.3896922686211395,
      "size": 1230,
      "loadReceiveTime": 94
    }
  ],
  "95": [
    {
      "id": 188,
      "type": 0.9518752757043785,
      "size": 1886,
      "loadReceiveTime": 95
    },
    {
      "id": 189,
      "type": 0.3314143421547817,
      "size": 1057,
      "loadReceiveTime": 95
    }
  ],
  "96": [
    {
      "id": 190,
      "type": 0.8424936236194922,
      "size": 3000,
      "loadReceiveTime": 96
    },
    {
      "id": 191,
      "type": 0.07236482273488987,
      "size": 2237,
      "loadReceiveTime": 96
    }
  ],
  "97": [
    {
      "id": 192,
      "type": 0.25747887499534095,
      "size": 588,
      "loadReceiveTime": 97
    },
    {
      "id": 193,
      "type": 0.8788795214840599,
      "size": 534,
      "loadReceiveTime": 97
    }
  ],
  "98": [
    {
      "id": 194,
      "type": 0.8720014652001613,
      "size": 2715,
      "loadReceiveTime": 98
    },
    {
      "id": 195,
      "type": 0.10865205681191292,
      "size": 329,
      "loadReceiveTime": 98
    }
  ],
  "99": [
    {
      "id": 196,
      "type": 0.8381391212973417,
      "size": 662,
      "loadReceiveTime": 99
    },
    {
      "id": 197,
      "type": 0.366682611222386,
      "size": 155,
      "loadReceiveTime": 99
    }
  ],
  "100": [
    {
      "id": 198,
      "type": 0.20488564147881005,
      "size": 274,
      "loadReceiveTime": 100
    },
    {
      "id": 199,
      "type": 0.48328913103775184,
      "size": 457,
      "loadReceiveTime": 100
    }
  ]
}