{
  "0": [
    {
      "id": 0,
      "type": 0.6731724710888392,
      "size": 1580,
      "loadReceiveTime": 0
    },
    {
      "id": 1,
      "type": 0.9832824308176638,
      "size": 643,
      "loadReceiveTime": 0
    },
    {
      "id": 2,
      "type": 0.38913693486247714,
      "size": 145,
      "loadReceiveTime": 0
    },
    {
      "id": 3,
      "type": 0.9206117929632371,
      "size": 2072,
      "loadReceiveTime": 0
    },
    {
      "id": 4,
      "type": 0.28222772499994986,
      "size": 778,
      "loadReceiveTime": 0
    }
  ],
  "1": [
    {
      "id": 5,
      "type": 0.31308981581307593,
      "size": 1278,
      "loadReceiveTime": 1
    },
    {
      "id": 6,
      "type": 0.28822532733424566,
      "size": 406,
      "loadReceiveTime": 1
    },
    {
      "id": 7,
      "type": 0.8803400959341086,
      "size": 265,
      "loadReceiveTime": 1
    },
    {
      "id": 8,
      "type": 0.07593938516994836,
      "size": 1318,
      "loadReceiveTime": 1
    },
    {
      "id": 9,
      "type": 0.8674056735526519,
      "size": 378,
      "loadReceiveTime": 1
    }
  ],
  "2": [
    {
      "id": 10,
      "type": 0.5801099810406061,
      "size": 2112,
      "loadReceiveTime": 2
    },
    {
      "id": 11,
      "type": 0.6323134248124243,
      "size": 181,
      "loadReceiveTime": 2
    },
    {
      "id": 12,
      "type": 0.16011799761366863,
      "size": 907,
      "loadReceiveTime": 2
    },
    {
      "id": 13,
      "type": 0.2954467248638777,
      "size": 2757,
      "loadReceiveTime": 2
    },
    {
      "id": 14,
      "type": 0.6682708004025355,
      "size": 295,
      "loadReceiveTime": 2
    }
  ],
  "3": [
    {
      "id": 15,
      "type": 0.7359685145793582,
      "size": 1207,
      "loadReceiveTime": 3
    },
    {
      "id": 16,
      "type": 0.17644237740408109,
      "size": 1247,
      "loadReceiveTime": 3
    },
    {
      "id": 17,
      "type": 0.15498706276104168,
      "size": 1023,
      "loadReceiveTime": 3
    },
    {
      "id": 18,
      "type": 0.2519441000058955,
      "size": 724,
      "loadReceiveTime": 3
    },
    {
      "id": 19,
      "type": 0.16520730294250963,
      "size": 477,
      "loadReceiveTime": 3
    }
  ],
  "4": [
    {
      "id": 20,
      "type": 0.9962565260296246,
      "size": 1061,
      "loadReceiveTime": 4
    },
    {
      "id": 21,
      "type": 0.649645990173396,
      "size": 155,
      "loadReceiveTime": 4
    },
    {
      "id": 22,
      "type": 0.20402818056485916,
      "size": 181,
      "loadReceiveTime": 4
    },
    {
      "id": 23,
      "type": 0.34559712282003385,
      "size": 448,
      "loadReceiveTime": 4
    },
    {
      "id": 24,
      "type": 0.3303598430074788,
      "size": 1799,
      "loadReceiveTime": 4
    }
  ],
  "5": [
    {
      "id": 25,
      "type": 0.08862247874994322,
      "size": 253,
      "loadReceiveTime": 5
    },
    {
      "id": 26,
      "type": 0.054553335756181154,
      "size": 1333,
      "loadReceiveTime": 5
    },
    {
      "id": 27,
      "type": 0.9954087611037397,
      "size": 94,
      "loadReceiveTime": 5
    },
    {
      "id": 28,
      "type": 0.3399362136303252,
      "size": 1303,
      "loadReceiveTime": 5
    },
    {
      "id": 29,
      "type": 0.4825718190342332,
      "size": 892,
      "loadReceiveTime": 5
    }
  ],
  "6": [
    {
      "id": 30,
      "type": 0.8602235757265271,
      "size": 17,
      "loadReceiveTime": 6
    },
    {
      "id": 31,
      "type": 0.5993252093514088,
      "size": 2306,
      "loadReceiveTime": 6
    },
    {
      "id": 32,
      "type": 0.2995430277442519,
      "size": 201,
      "loadReceiveTime": 6
    },
    {
      "id": 33,
      "type": 0.7482412356465338,
      "size": 3749,
      "loadReceiveTime": 6
    },
    {
      "id": 34,
      "type": 0.7232245551551977,
      "size": 660,
      "loadReceiveTime": 6
    }
  ],
  "7": [
    {
      "id": 35,
      "type": 0.9368028176742742,
      "size": 2185,
      "loadReceiveTime": 7
    },
    {
      "id": 36,
      "type": 0.6838155431051489,
      "size": 687,
      "loadReceiveTime": 7
    },
    {
      "id": 37,
      "type": 0.28135598118038607,
      "size": 521,
      "loadReceiveTime": 7
    },
    {
      "id": 38,
      "type": 0.604849754773386,
      "size": 1301,
      "loadReceiveTime": 7
    },
    {
      "id": 39,
      "type": 0.43621083976625274,
      "size": 1553,
      "loadReceiveTime": 7
    }
  ],
  "8": [
    {
      "id": 40,
      "type": 0.8359267476115386,
      "size": 877,
      "loadReceiveTime": 8
    },
    {
      "id": 41,
      "type": 0.5732238501911253,
      "size": 976,
      "loadReceiveTime": 8
    },
    {
      "id": 42,
      "type": 0.728116510967906,
      "size": 856,
      "loadReceiveTime": 8
    },
    {
      "id": 43,
      "type": 0.5476977401101852,
      "size": 598,
      "loadReceiveTime": 8
    },
    {
      "id": 44,
      "type": 0.7726690711524806,
      "size": 546,
      "loadReceiveTime": 8
    }
  ],
  "9": [
    {
      "id": 45,
      "type": 0.3891256099476492,
      "size": 338,
      "loadReceiveTime": 9
    },
    {
      "id": 46,
      "type": 0.5727048195173539,
      "size": 698,
      "loadReceiveTime": 9
    },
    {
      "id": 47,
      "type": 0.017189259363585396,
      "size": 1867,
      "loadReceiveTime": 9
    },
    {
      "id": 48,
      "type": 0.5050497165374337,
      "size": 960,
      "loadReceiveTime": 9
    },
    {
      "id": 49,
      "type": 0.5526549854966829,
      "size": 1557,
      "loadReceiveTime": 9
    }
  ],
  "10": [
    {
      "id": 50,
      "type": 0.6213444204825114,
      "size": 766,
      "loadReceiveTime": 10
    },
    {
      "id": 51,
      "type": 0.00970407042075716,
      "size": 214,
      "loadReceiveTime": 10
    },
    {
      "id": 52,
      "type": 0.11261600337402511,
      "size": 1870,
      "loadReceiveTime": 10
    },
    {
      "id": 53,
      "type": 0.2662862960801935,
      "size": 471,
      "loadReceiveTime": 10
    },
    {
      "id": 54,
      "type": 0.683833833755942,
      "size": 256,
      "loadReceiveTime": 10
    }
  ],
  "11": [
    {
      "id": 55,
      "type": 0.7367574656734297,
      "size": 731,
      "loadReceiveTime": 11
    },
    {
      "id": 56,
      "type": 0.8256322602695851,
      "size": 203,
      "loadReceiveTime": 11
    },
    {
      "id": 57,
      "type": 0.09953509400847427,
      "size": 104,
      "loadReceiveTime": 11
    },
    {
      "id": 58,
      "type": 0.7053753727607053,
      "size": 696,
      "loadReceiveTime": 11
    },
    {
      "id": 59,
      "type": 0.6729513414584849,
      "size": 1150,
      "loadReceiveTime": 11
    }
  ],
  "12": [
    {
      "id": 60,
      "type": 0.33414953925806845,
      "size": 917,
      "loadReceiveTime": 12
    },
    {
      "id": 61,
      "type": 0.11957512085970912,
      "size": 168,
      "loadReceiveTime": 12
    },
    {
      "id": 62,
      "type": 0.5311102629063476,
      "size": 256,
      "loadReceiveTime": 12
    },
    {
      "id": 63,
      "type": 0.6714319226013343,
      "size": 1186,
      "loadReceiveTime": 12
    },
    {
      "id": 64,
      "type": 0.8869716893034667,
      "size": 938,
      "loadReceiveTime": 12
    }
  ],
  "13": [
    {
      "id": 65,
      "type": 0.37302781294618037,
      "size": 1243,
      "loadReceiveTime": 13
    },
    {
      "id": 66,
      "type": 0.38855438822350385,
      "size": 2249,
      "loadReceiveTime": 13
    },
    {
      "id": 67,
      "type": 0.23027313079680845,
      "size": 291,
      "loadReceiveTime": 13
    },
    {
      "id": 68,
      "type": 0.6819963413800123,
      "size": 35,
      "loadReceiveTime": 13
    },
    {
      "id": 69,
      "type": 0.3595543841073152,
      "size": 370,
      "loadReceiveTime": 13
    }
  ],
  "14": [
    {
      "id": 70,
      "type": 0.5719408929226437,
      "size": 431,
      "loadReceiveTime": 14
    },
    {
      "id": 71,
      "type": 0.0992551152970611,
      "size": 357,
      "loadReceiveTime": 14
    },
    {
      "id": 72,
      "type": 0.34803686388985433,
      "size": 1143,
      "loadReceiveTime": 14
    },
    {
      "id": 73,
      "type": 0.02800181850620831,
      "size": 1106,
      "loadReceiveTime": 14
    },
    {
      "id": 74,
      "type": 0.4754088109031789,
      "size": 1558,
      "loadReceiveTime": 14
    }
  ],
  "15": [
    {
      "id": 75,
      "type": 0.5909159863432869,
      "size": 11,
      "loadReceiveTime": 15
    },
    {
      "id": 76,
      "type": 0.9185957777082574,
      "size": 812,
      "loadReceiveTime": 15
    },
    {
      "id": 77,
      "type": 0.7763245975699646,
      "size": 3053,
      "loadReceiveTime": 15
    },
    {
      "id": 78,
      "type": 0.055935637919845016,
      "size": 929,
      "loadReceiveTime": 15
    },
    {
      "id": 79,
      "type": 0.6073964031289298,
      "size": 978,
      "loadReceiveTime": 15
    }
  ],
  "16": [
    {
      "id": 80,
      "type": 0.8449432288856582,
      "size": 227,
      "loadReceiveTime": 16
    },
    {
      "id": 81,
      "type": 0.12708745017186107,
      "size": 54,
      "loadReceiveTime": 16
    },
    {
      "id": 82,
      "type": 0.5610653718021585,
      "size": 266,
      "loadReceiveTime": 16
    },
    {
      "id": 83,
      "type": 0.3009449104499211,
      "size": 535,
      "loadReceiveTime": 16
    },
    {
      "id": 84,
      "type": 0.40676971270509354,
      "size": 236,
      "loadReceiveTime": 16
    }
  ],
  "17": [
    {
      "id": 85,
      "type": 0.6599882603924809,
      "size": 139,
      "loadReceiveTime": 17
    },
    {
      "id": 86,
      "type": 0.2630771765221436,
      "size": 3642,
      "loadReceiveTime": 17
    },
    {
      "id": 87,
      "type": 0.8419227880182143,
      "size": 539,
      "loadReceiveTime": 17
    },
    {
      "id": 88,
      "type": 0.47510038942187816,
      "size": 1402,
      "loadReceiveTime": 17
    },
    {
      "id": 89,
      "type": 0.8189007637761301,
      "size": 1035,
      "loadReceiveTime": 17
    }
  ],
  "18": [
    {
      "id": 90,
      "type": 0.14287400356932745,
      "size": 117,
      "loadReceiveTime": 18
    },
    {
      "id": 91,
      "type": 0.8435132489756252,
      "size": 110,
      "loadReceiveTime": 18
    },
    {
      "id": 92,
      "type": 0.44122129844714286,
      "size": 921,
      "loadReceiveTime": 18
    },
    {
      "id": 93,
      "type": 0.36687934161458147,
      "size": 173,
      "loadReceiveTime": 18
    },
    {
      "id": 94,
      "type": 0.00034107875831201895,
      "size": 58,
      "loadReceiveTime": 18
    }
  ],
  "19": [
    {
      "id": 95,
      "type": 0.10761946624052743,
      "size": 139,
      "loadReceiveTime": 19
    },
    {
      "id": 96,
      "type": 0.14330258111266492,
      "size": 2167,
      "loadReceiveTime": 19
    },
    {
      "id": 97,
      "type": 0.06137945530104094,
      "size": 516,
      "loadReceiveTime": 19
    },
    {
      "id": 98,
      "type": 0.10812177541835277,
      "size": 783,
      "loadReceiveTime": 19
    },
    {
      "id": 99,
      "type": 0.18102803560872238,
      "size": 75,
      "loadReceiveTime": 19
    }
  ],
  "20": [
    {
      "id": 100,
      "type": 0.3588412622740098,
      "size": 444,
      "loadReceiveTime": 20
    },
    {
      "id": 101,
      "type": 0.7198917653670207,
      "size": 27,
      "loadReceiveTime": 20
    },
    {
      "id": 102,
      "type": 0.8409450300378825,
      "size": 1390,
      "loadReceiveTime": 20
    },
    {
      "id": 103,
      "type": 0.8697818152882995,
      "size": 1464,
      "loadReceiveTime": 20
    },
    {
      "id": 104,
      "type": 0.01669836679586334,
      "size": 217,
      "loadReceiveTime": 20
    }
  ],
  "21": [
    {
      "id": 105,
      "type": 0.019140059764267914,
      "size": 1859,
      "loadReceiveTime": 21
    },
    {
      "id": 106,
      "type": 0.5798818633785836,
      "size": 1822,
      "loadReceiveTime": 21
    },
    {
      "id": 107,
      "type": 0.4134850470856022,
      "size": 1524,
      "loadReceiveTime": 21
    },
    {
      "id": 108,
      "type": 0.36779625879466393,
      "size": 300,
      "loadReceiveTime": 21
    },
    {
      "id": 109,
      "type": 0.8408735844980455,
      "size": 227,
      "loadReceiveTime": 21
    }
  ],
  "22": [
    {
      "id": 110,
      "type": 0.9618392460798217,
      "size": 1359,
      "loadReceiveTime": 22
    },
    {
      "id": 111,
      "type": 0.5054062294277775,
      "size": 242,
      "loadReceiveTime": 22
    },
    {
      "id": 112,
      "type": 0.45607006717259124,
      "size": 401,
      "loadReceiveTime": 22
    },
    {
      "id": 113,
      "type": 0.23354289606915413,
      "size": 426,
      "loadReceiveTime": 22
    },
    {
      "id": 114,
      "type": 0.07430021280928156,
      "size": 1558,
      "loadReceiveTime": 22
    }
  ],
  "23": [
    {
      "id": 115,
      "type": 0.3131192974395358,
      "size": 474,
      "loadReceiveTime": 23
    },
    {
      "id": 116,
      "type": 0.28110930783186205,
      "size": 889,
      "loadReceiveTime": 23
    },
    {
      "id": 117,
      "type": 0.18507650156873034,
      "size": 923,
      "loadReceiveTime": 23
    },
    {
      "id": 118,
      "type": 0.6514814860722866,
      "size": 735,
      "loadReceiveTime": 23
    },
    {
      "id": 119,
      "type": 0.17769117879514584,
      "size": 2019,
      "loadReceiveTime": 23
    }
  ],
  "24": [
    {
      "id": 120,
      "type": 0.7498781980366334,
      "size": 2326,
      "loadReceiveTime": 24
    },
    {
      "id": 121,
      "type": 0.03460396717035885,
      "size": 1816,
      "loadReceiveTime": 24
    },
    {
      "id": 122,
      "type": 0.017873966922609563,
      "size": 915,
      "loadReceiveTime": 24
    },
    {
      "id": 123,
      "type": 0.7986806334210923,
      "size": 174,
      "loadReceiveTime": 24
    },
    {
      "id": 124,
      "type": 0.30301267163201584,
      "size": 1097,
      "loadReceiveTime": 24
    }
  ],
  "25": [
    {
      "id": 125,
      "type": 0.7147991772483153,
      "size": 1195,
      "loadReceiveTime": 25
    },
    {
      "id": 126,
      "type": 0.6905347676198221,
      "size": 832,
      "loadReceiveTime": 25
    },
    {
      "id": 127,
      "type": 0.21835329470551956,
      "size": 583,
      "loadReceiveTime": 25
    },
    {
      "id": 128,
      "type": 0.5807511897523707,
      "size": 1710,
      "loadReceiveTime": 25
    },
    {
      "id": 129,
      "type": 0.2949519049356728,
      "size": 693,
      "loadReceiveTime": 25
    }
  ],
  "26": [
    {
      "id": 130,
      "type": 0.7928914588344489,
      "size": 381,
      "loadReceiveTime": 26
    },
    {
      "id": 131,
      "type": 0.2914077254871559,
      "size": 130,
      "loadReceiveTime": 26
    },
    {
      "id": 132,
      "type": 0.12525875887496674,
      "size": 957,
      "loadReceiveTime": 26
    },
    {
      "id": 133,
      "type": 0.3961467816854045,
      "size": 1477,
      "loadReceiveTime": 26
    },
    {
      "id": 134,
      "type": 0.9972924861207881,
      "size": 1126,
      "loadReceiveTime": 26
    }
  ],
  "27": [
    {
      "id": 135,
      "type": 0.904504764127587,
      "size": 1693,
      "loadReceiveTime": 27
    },
    {
      "id": 136,
      "type": 0.7166424053091949,
      "size": 1213,
      "loadReceiveTime": 27
    },
    {
      "id": 137,
      "type": 0.445533172675153,
      "size": 200,
      "loadReceiveTime": 27
    },
    {
      "id": 138,
      "type": 0.5774126456429096,
      "size": 516,
      "loadReceiveTime": 27
    },
    {
      "id": 139,
      "type": 0.3061133248305017,
      "size": 509,
      "loadReceiveTime": 27
    }
  ],
  "28": [
    {
      "id": 140,
      "type": 0.6991259199130524,
      "size": 48,
      "loadReceiveTime": 28
    },
    {
      "id": 141,
      "type": 0.3258899215342681,
      "size": 667,
      "loadReceiveTime": 28
    },
    {
      "id": 142,
      "type": 0.6390849659493179,
      "size": 262,
      "loadReceiveTime": 28
    },
    {
      "id": 143,
      "type": 0.6860373464129164,
      "size": 1808,
      "loadReceiveTime": 28
    },
    {
      "id": 144,
      "type": 0.53448015679988,
      "size": 189,
      "loadReceiveTime": 28
    }
  ],
  "29": [
    {
      "id": 145,
      "type": 0.21686312866961055,
      "size": 1581,
      "loadReceiveTime": 29
    },
    {
      "id": 146,
      "type": 0.5933161013321224,
      "size": 1044,
      "loadReceiveTime": 29
    },
    {
      "id": 147,
      "type": 0.9190429798944806,
      "size": 816,
      "loadReceiveTime": 29
    },
    {
      "id": 148,
      "type": 0.3294429969749386,
      "size": 476,
      "loadReceiveTime": 29
    },
    {
      "id": 149,
      "type": 0.5846687754319861,
      "size": 843,
      "loadReceiveTime": 29
    }
  ],
  "30": [
    {
      "id": 150,
      "type": 0.6691504959185466,
      "size": 636,
      "loadReceiveTime": 30
    },
    {
      "id": 151,
      "type": 0.6531231964614486,
      "size": 1070,
      "loadReceiveTime": 30
    },
    {
      "id": 152,
      "type": 0.07363368508192059,
      "size": 3312,
      "loadReceiveTime": 30
    },
    {
      "id": 153,
      "type": 0.1035038294282784,
      "size": 2537,
      "loadReceiveTime": 30
    },
    {
      "id": 154,
      "type": 0.8817439402433505,
      "size": 611,
      "loadReceiveTime": 30
    }
  ],
  "31": [
    {
      "id": 155,
      "type": 0.17564138156858333,
      "size": 616,
      "loadReceiveTime": 31
    },
    {
      "id": 156,
      "type": 0.6135598546653542,
      "size": 921,
      "loadReceiveTime": 31
    },
    {
      "id": 157,
      "type": 0.8911866348935373,
      "size": 1599,
      "loadReceiveTime": 31
    },
    {
      "id": 158,
      "type": 0.6075998408434342,
      "size": 233,
      "loadReceiveTime": 31
    },
    {
      "id": 159,
      "type": 0.19287983272768372,
      "size": 1103,
      "loadReceiveTime": 31
    }
  ],
  "32": [
    {
      "id": 160,
      "type": 0.39818114579779196,
      "size": 371,
      "loadReceiveTime": 32
    },
    {
      "id": 161,
      "type": 0.11329565055105961,
      "size": 325,
      "loadReceiveTime": 32
    },
    {
      "id": 162,
      "type": 0.6691608222352083,
      "size": 390,
      "loadReceiveTime": 32
    },
    {
      "id": 163,
      "type": 0.5911741410846321,
      "size": 436,
      "loadReceiveTime": 32
    },
    {
      "id": 164,
      "type": 0.3029900125874374,
      "size": 1216,
      "loadReceiveTime": 32
    }
  ],
  "33": [
    {
      "id": 165,
      "type": 0.0632327782154063,
      "size": 144,
      "loadReceiveTime": 33
    },
    {
      "id": 166,
      "type": 0.7767524505928487,
      "size": 455,
      "loadReceiveTime": 33
    },
    {
      "id": 167,
      "type": 0.8851384168688088,
      "size": 281,
      "loadReceiveTime": 33
    },
    {
      "id": 168,
      "type": 0.7707013939760547,
      "size": 2446,
      "loadReceiveTime": 33
    },
    {
      "id": 169,
      "type": 0.4135632878380513,
      "size": 19,
      "loadReceiveTime": 33
    }
  ],
  "34": [
    {
      "id": 170,
      "type": 0.0713754722257589,
      "size": 537,
      "loadReceiveTime": 34
    },
    {
      "id": 171,
      "type": 0.737648647616022,
      "size": 104,
      "loadReceiveTime": 34
    },
    {
      "id": 172,
      "type": 0.8744186690502325,
      "size": 4837,
      "loadReceiveTime": 34
    },
    {
      "id": 173,
      "type": 0.3923194442765088,
      "size": 283,
      "loadReceiveTime": 34
    },
    {
      "id": 174,
      "type": 0.5999888340855464,
      "size": 3259,
      "loadReceiveTime": 34
    }
  ],
  "35": [
    {
      "id": 175,
      "type": 0.7641134152759073,
      "size": 3081,
      "loadReceiveTime": 35
    },
    {
      "id": 176,
      "type": 0.013876653492389535,
      "size": 416,
      "loadReceiveTime": 35
    },
    {
      "id": 177,
      "type": 0.6200088703353897,
      "size": 511,
      "loadReceiveTime": 35
    },
    {
      "id": 178,
      "type": 0.8428646675024043,
      "size": 158,
      "loadReceiveTime": 35
    },
    {
      "id": 179,
      "type": 0.19917803793291222,
      "size": 58,
      "loadReceiveTime": 35
    }
  ],
  "36": [
    {
      "id": 180,
      "type": 0.18795187431160798,
      "size": 265,
      "loadReceiveTime": 36
    },
    {
      "id": 181,
      "type": 0.5447160898457766,
      "size": 1222,
      "loadReceiveTime": 36
    },
    {
      "id": 182,
      "type": 0.9110200788561504,
      "size": 456,
      "loadReceiveTime": 36
    },
    {
      "id": 183,
      "type": 0.014837191219044144,
      "size": 1120,
      "loadReceiveTime": 36
    },
    {
      "id": 184,
      "type": 0.5824711918401411,
      "size": 19,
      "loadReceiveTime": 36
    }
  ],
  "37": [
    {
      "id": 185,
      "type": 0.36863367401933034,
      "size": 1115,
      "loadReceiveTime": 37
    },
    {
      "id": 186,
      "type": 0.36145493784943716,
      "size": 405,
      "loadReceiveTime": 37
    },
    {
      "id": 187,
      "type": 0.3578004060805611,
      "size": 2096,
      "loadReceiveTime": 37
    },
    {
      "id": 188,
      "type": 0.15090479035496407,
      "size": 3349,
      "loadReceiveTime": 37
    },
    {
      "id": 189,
      "type": 0.7748467602743365,
      "size": 1562,
      "loadReceiveTime": 37
    }
  ],
  "38": [
    {
      "id": 190,
      "type": 0.09178753905605341,
      "size": 301,
      "loadReceiveTime": 38
    },
    {
      "id": 191,
      "type": 0.09512133764222552,
      "size": 3469,
      "loadReceiveTime": 38
    },
    {
      "id": 192,
      "type": 0.07978679020439294,
      "size": 204,
      "loadReceiveTime": 38
    },
    {
      "id": 193,
      "type": 0.4626335475369947,
      "size": 180,
      "loadReceiveTime": 38
    },
    {
      "id": 194,
      "type": 0.23034147590140752,
      "size": 845,
      "loadReceiveTime": 38
    }
  ],
  "39": [
    {
      "id": 195,
      "type": 0.5402188721673402,
      "size": 624,
      "loadReceiveTime": 39
    },
    {
      "id": 196,
      "type": 0.8093456459688335,
      "size": 3505,
      "loadReceiveTime": 39
    },
    {
      "id": 197,
      "type": 0.5909029032332365,
      "size": 41,
      "loadReceiveTime": 39
    },
    {
      "id": 198,
      "type": 0.6424316149248666,
      "size": 1541,
      "loadReceiveTime": 39
    },
    {
      "id": 199,
      "type": 0.9129220072760826,
      "size": 104,
      "loadReceiveTime": 39
    }
  ],
  "40": [
    {
      "id": 200,
      "type": 0.6446712574329947,
      "size": 827,
      "loadReceiveTime": 40
    },
    {
      "id": 201,
      "type": 0.38346701433821084,
      "size": 104,
      "loadReceiveTime": 40
    },
    {
      "id": 202,
      "type": 0.458033048726157,
      "size": 1769,
      "loadReceiveTime": 40
    },
    {
      "id": 203,
      "type": 0.10071635927991607,
      "size": 491,
      "loadReceiveTime": 40
    },
    {
      "id": 204,
      "type": 0.21431033049173842,
      "size": 1188,
      "loadReceiveTime": 40
    }
  ],
  "41": [
    {
      "id": 205,
      "type": 0.10803575848011193,
      "size": 101,
      "loadReceiveTime": 41
    },
    {
      "id": 206,
      "type": 0.6259941552981811,
      "size": 1089,
      "loadReceiveTime": 41
    },
    {
      "id": 207,
      "type": 0.8308430236563809,
      "size": 20,
      "loadReceiveTime": 41
    },
    {
      "id": 208,
      "type": 0.7868597198332647,
      "size": 870,
      "loadReceiveTime": 41
    },
    {
      "id": 209,
      "type": 0.3811622244799473,
      "size": 207,
      "loadReceiveTime": 41
    }
  ],
  "42": [
    {
      "id": 210,
      "type": 0.9764325026806924,
      "size": 1657,
      "loadReceiveTime": 42
    },
    {
      "id": 211,
      "type": 0.5722480157058085,
      "size": 280,
      "loadReceiveTime": 42
    },
    {
      "id": 212,
      "type": 0.7743316505567404,
      "size": 1442,
      "loadReceiveTime": 42
    },
    {
      "id": 213,
      "type": 0.31686222802370745,
      "size": 438,
      "loadReceiveTime": 42
    },
    {
      "id": 214,
      "type": 0.38094329397847004,
      "size": 151,
      "loadReceiveTime": 42
    }
  ],
  "43": [
    {
      "id": 215,
      "type": 0.7446877609240015,
      "size": 107,
      "loadReceiveTime": 43
    },
    {
      "id": 216,
      "type": 0.25584545924521773,
      "size": 728,
      "loadReceiveTime": 43
    },
    {
      "id": 217,
      "type": 0.04137420201453157,
      "size": 566,
      "loadReceiveTime": 43
    },
    {
      "id": 218,
      "type": 0.5784277766863053,
      "size": 1005,
      "loadReceiveTime": 43
    },
    {
      "id": 219,
      "type": 0.9731748586729905,
      "size": 1090,
      "loadReceiveTime": 43
    }
  ],
  "44": [
    {
      "id": 220,
      "type": 0.10702367755686404,
      "size": 2025,
      "loadReceiveTime": 44
    },
    {
      "id": 221,
      "type": 0.48212810860986166,
      "size": 120,
      "loadReceiveTime": 44
    },
    {
      "id": 222,
      "type": 0.4184094719049243,
      "size": 604,
      "loadReceiveTime": 44
    },
    {
      "id": 223,
      "type": 0.10278392309619222,
      "size": 493,
      "loadReceiveTime": 44
    },
    {
      "id": 224,
      "type": 0.03219109468314452,
      "size": 1794,
      "loadReceiveTime": 44
    }
  ],
  "45": [
    {
      "id": 225,
      "type": 0.36262223086708856,
      "size": 3270,
      "loadReceiveTime": 45
    },
    {
      "id": 226,
      "type": 0.5818642893612567,
      "size": 63,
      "loadReceiveTime": 45
    },
    {
      "id": 227,
      "type": 0.3618049122134914,
      "size": 271,
      "loadReceiveTime": 45
    },
    {
      "id": 228,
      "type": 0.8445923404604083,
      "size": 314,
      "loadReceiveTime": 45
    },
    {
      "id": 229,
      "type": 0.6644486406312864,
      "size": 1055,
      "loadReceiveTime": 45
    }
  ],
  "46": [
    {
      "id": 230,
      "type": 0.8457144938071774,
      "size": 423,
      "loadReceiveTime": 46
    },
    {
      "id": 231,
      "type": 0.05382455071364256,
      "size": 1537,
      "loadReceiveTime": 46
    },
    {
      "id": 232,
      "type": 0.19995712045014913,
      "size": 105,
      "loadReceiveTime": 46
    },
    {
      "id": 233,
      "type": 0.3995525058091691,
      "size": 452,
      "loadReceiveTime": 46
    },
    {
      "id": 234,
      "type": 0.416547208958133,
      "size": 1955,
      "loadReceiveTime": 46
    }
  ],
  "47": [
    {
      "id": 235,
      "type": 0.006602066425184905,
      "size": 1759,
      "loadReceiveTime": 47
    },
    {
      "id": 236,
      "type": 0.5882616593399301,
      "size": 69,
      "loadReceiveTime": 47
    },
    {
      "id": 237,
      "type": 0.6746456900675879,
      "size": 3210,
      "loadReceiveTime": 47
    },
    {
      "id": 238,
      "type": 0.3969101159423125,
      "size": 1468,
      "loadReceiveTime": 47
    },
    {
      "id": 239,
      "type": 0.4790291430248397,
      "size": 2112,
      "loadReceiveTime": 47
    }
  ],
  "48": [
    {
      "id": 240,
      "type": 0.11535938588241401,
      "size": 167,
      "loadReceiveTime": 48
    },
    {
      "id": 241,
      "type": 0.8293807279527303,
      "size": 671,
      "loadReceiveTime": 48
    },
    {
      "id": 242,
      "type": 0.4097799813558347,
      "size": 496,
      "loadReceiveTime": 48
    },
    {
      "id": 243,
      "type": 0.8279787820122824,
      "size": 1185,
      "loadReceiveTime": 48
    },
    {
      "id": 244,
      "type": 0.5990183513061167,
      "size": 27,
      "loadReceiveTime": 48
    }
  ],
  "49": [
    {
      "id": 245,
      "type": 0.7383693259481796,
      "size": 833,
      "loadReceiveTime": 49
    },
    {
      "id": 246,
      "type": 0.37888213008986726,
      "size": 201,
      "loadReceiveTime": 49
    },
    {
      "id": 247,
      "type": 0.9254639377194598,
      "size": 1639,
      "loadReceiveTime": 49
    },
    {
      "id": 248,
      "type": 0.9640755033337878,
      "size": 132,
      "loadReceiveTime": 49
    },
    {
      "id": 249,
      "type": 0.25407497360277653,
      "size": 626,
      "loadReceiveTime": 49
    }
  ],
  "50": [
    {
      "id": 250,
      "type": 0.652485266709895,
      "size": 152,
      "loadReceiveTime": 50
    },
    {
      "id": 251,
      "type": 0.302306343730784,
      "size": 282,
      "loadReceiveTime": 50
    },
    {
      "id": 252,
      "type": 0.3889988111326135,
      "size": 607,
      "loadReceiveTime": 50
    },
    {
      "id": 253,
      "type": 0.0013747432614150679,
      "size": 17,
      "loadReceiveTime": 50
    },
    {
      "id": 254,
      "type": 0.7361575214810405,
      "size": 722,
      "loadReceiveTime": 50
    }
  ],
  "51": [
    {
      "id": 255,
      "type": 0.752924943779133,
      "size": 2877,
      "loadReceiveTime": 51
    },
    {
      "id": 256,
      "type": 0.15825238891390891,
      "size": 306,
      "loadReceiveTime": 51
    },
    {
      "id": 257,
      "type": 0.004511822530397724,
      "size": 2390,
      "loadReceiveTime": 51
    },
    {
      "id": 258,
      "type": 0.832677124327933,
      "size": 452,
      "loadReceiveTime": 51
    },
    {
      "id": 259,
      "type": 0.3508392040913506,
      "size": 1083,
      "loadReceiveTime": 51
    }
  ],
  "52": [
    {
      "id": 260,
      "type": 0.09027847212575524,
      "size": 1840,
      "loadReceiveTime": 52
    },
    {
      "id": 261,
      "type": 0.8095523418837962,
      "size": 3393,
      "loadReceiveTime": 52
    },
    {
      "id": 262,
      "type": 0.9417671157087113,
      "size": 155,
      "loadReceiveTime": 52
    },
    {
      "id": 263,
      "type": 0.5201344169016446,
      "size": 257,
      "loadReceiveTime": 52
    },
    {
      "id": 264,
      "type": 0.6374229002362788,
      "size": 903,
      "loadReceiveTime": 52
    }
  ],
  "53": [
    {
      "id": 265,
      "type": 0.013141452064777459,
      "size": 129,
      "loadReceiveTime": 53
    },
    {
      "id": 266,
      "type": 0.6718056699922037,
      "size": 605,
      "loadReceiveTime": 53
    },
    {
      "id": 267,
      "type": 0.7777489944065972,
      "size": 1034,
      "loadReceiveTime": 53
    },
    {
      "id": 268,
      "type": 0.09674828692677284,
      "size": 1331,
      "loadReceiveTime": 53
    },
    {
      "id": 269,
      "type": 0.010929568239308018,
      "size": 1424,
      "loadReceiveTime": 53
    }
  ],
  "54": [
    {
      "id": 270,
      "type": 0.488971442876345,
      "size": 2904,
      "loadReceiveTime": 54
    },
    {
      "id": 271,
      "type": 0.7801625990853454,
      "size": 1041,
      "loadReceiveTime": 54
    },
    {
      "id": 272,
      "type": 0.9310142196539468,
      "size": 1148,
      "loadReceiveTime": 54
    },
    {
      "id": 273,
      "type": 0.7056778209682133,
      "size": 277,
      "loadReceiveTime": 54
    },
    {
      "id": 274,
      "type": 0.702235568875317,
      "size": 715,
      "loadReceiveTime": 54
    }
  ],
  "55": [
    {
      "id": 275,
      "type": 0.655731571425904,
      "size": 397,
      "loadReceiveTime": 55
    },
    {
      "id": 276,
      "type": 0.16270913790420827,
      "size": 832,
      "loadReceiveTime": 55
    },
    {
      "id": 277,
      "type": 0.9238236406940501,
      "size": 1592,
      "loadReceiveTime": 55
    },
    {
      "id": 278,
      "type": 0.20939718944206942,
      "size": 132,
      "loadReceiveTime": 55
    },
    {
      "id": 279,
      "type": 0.5054004604557563,
      "size": 1018,
      "loadReceiveTime": 55
    }
  ],
  "56": [
    {
      "id": 280,
      "type": 0.22656742699114063,
      "size": 36,
      "loadReceiveTime": 56
    },
    {
      "id": 281,
      "type": 0.7036384300655789,
      "size": 108,
      "loadReceiveTime": 56
    },
    {
      "id": 282,
      "type": 0.17091460799701386,
      "size": 1282,
      "loadReceiveTime": 56
    },
    {
      "id": 283,
      "type": 0.02528758049057278,
      "size": 1351,
      "loadReceiveTime": 56
    },
    {
      "id": 284,
      "type": 0.5521934781657754,
      "size": 637,
      "loadReceiveTime": 56
    }
  ],
  "57": [
    {
      "id": 285,
      "type": 0.7333477224272791,
      "size": 71,
      "loadReceiveTime": 57
    },
    {
      "id": 286,
      "type": 0.059842688284516,
      "size": 394,
      "loadReceiveTime": 57
    },
    {
      "id": 287,
      "type": 0.829709932460788,
      "size": 1639,
      "loadReceiveTime": 57
    },
    {
      "id": 288,
      "type": 0.7655571814646358,
      "size": 330,
      "loadReceiveTime": 57
    },
    {
      "id": 289,
      "type": 0.8722723465496542,
      "size": 564,
      "loadReceiveTime": 57
    }
  ],
  "58": [
    {
      "id": 290,
      "type": 0.13801800691492572,
      "size": 820,
      "loadReceiveTime": 58
    },
    {
      "id": 291,
      "type": 0.988461997741358,
      "size": 955,
      "loadReceiveTime": 58
    },
    {
      "id": 292,
      "type": 0.24972663898466352,
      "size": 249,
      "loadReceiveTime": 58
    },
    {
      "id": 293,
      "type": 0.9403831001134126,
      "size": 213,
      "loadReceiveTime": 58
    },
    {
      "id": 294,
      "type": 0.34335012394748077,
      "size": 2309,
      "loadReceiveTime": 58
    }
  ],
  "59": [
    {
      "id": 295,
      "type": 0.49800023017745443,
      "size": 153,
      "loadReceiveTime": 59
    },
    {
      "id": 296,
      "type": 0.9027868235983145,
      "size": 2387,
      "loadReceiveTime": 59
    },
    {
      "id": 297,
      "type": 0.4984717257218785,
      "size": 812,
      "loadReceiveTime": 59
    },
    {
      "id": 298,
      "type": 0.9306284742110118,
      "size": 875,
      "loadReceiveTime": 59
    },
    {
      "id": 299,
      "type": 0.4530969720073872,
      "size": 453,
      "loadReceiveTime": 59
    }
  ],
  "60": [
    {
      "id": 300,
      "type": 0.8779640690930803,
      "size": 52,
      "loadReceiveTime": 60
    },
    {
      "id": 301,
      "type": 0.8071478620546921,
      "size": 2768,
      "loadReceiveTime": 60
    },
    {
      "id": 302,
      "type": 0.2311745981226918,
      "size": 871,
      "loadReceiveTime": 60
    },
    {
      "id": 303,
      "type": 0.8836561551876001,
      "size": 1024,
      "loadReceiveTime": 60
    },
    {
      "id": 304,
      "type": 0.509132785402258,
      "size": 194,
      "loadReceiveTime": 60
    }
  ],
  "61": [
    {
      "id": 305,
      "type": 0.9396683885750343,
      "size": 107,
      "loadReceiveTime": 61
    },
    {
      "id": 306,
      "type": 0.7699967392163765,
      "size": 905,
      "loadReceiveTime": 61
    },
    {
      "id": 307,
      "type": 0.8363350497284978,
      "size": 377,
      "loadReceiveTime": 61
    },
    {
      "id": 308,
      "type": 0.5235664346491173,
      "size": 1527,
      "loadReceiveTime": 61
    },
    {
      "id": 309,
      "type": 0.2724124294154884,
      "size": 4139,
      "loadReceiveTime": 61
    }
  ],
  "62": [
    {
      "id": 310,
      "type": 0.9646419873383494,
      "size": 1887,
      "loadReceiveTime": 62
    },
    {
      "id": 311,
      "type": 0.29718964760553823,
      "size": 2059,
      "loadReceiveTime": 62
    },
    {
      "id": 312,
      "type": 0.24049049963432245,
      "size": 695,
      "loadReceiveTime": 62
    },
    {
      "id": 313,
      "type": 0.1715303475561667,
      "size": 317,
      "loadReceiveTime": 62
    },
    {
      "id": 314,
      "type": 0.8890615713610965,
      "size": 1642,
      "loadReceiveTime": 62
    }
  ],
  "63": [
    {
      "id": 315,
      "type": 0.30658341385302723,
      "size": 542,
      "loadReceiveTime": 63
    },
    {
      "id": 316,
      "type": 0.9347514439324234,
      "size": 173,
      "loadReceiveTime": 63
    },
    {
      "id": 317,
      "type": 0.5984947942219638,
      "size": 531,
      "loadReceiveTime": 63
    },
    {
      "id": 318,
      "type": 0.4143196476757942,
      "size": 796,
      "loadReceiveTime": 63
    },
    {
      "id": 319,
      "type": 0.30170521051851096,
      "size": 1716,
      "loadReceiveTime": 63
    }
  ],
  "64": [
    {
      "id": 320,
      "type": 0.3550426962811397,
      "size": 161,
      "loadReceiveTime": 64
    },
    {
      "id": 321,
      "type": 0.36059333983927355,
      "size": 156,
      "loadReceiveTime": 64
    },
    {
      "id": 322,
      "type": 0.5807778323179791,
      "size": 102,
      "loadReceiveTime": 64
    },
    {
      "id": 323,
      "type": 0.5220554234820987,
      "size": 577,
      "loadReceiveTime": 64
    },
    {
      "id": 324,
      "type": 0.8957107012501306,
      "size": 181,
      "loadReceiveTime": 64
    }
  ],
  "65": [
    {
      "id": 325,
      "type": 0.9426268892244545,
      "size": 41,
      "loadReceiveTime": 65
    },
    {
      "id": 326,
      "type": 0.5523396027185747,
      "size": 450,
      "loadReceiveTime": 65
    },
    {
      "id": 327,
      "type": 0.15247659158436533,
      "size": 95,
      "loadReceiveTime": 65
    },
    {
      "id": 328,
      "type": 0.7749335076892656,
      "size": 857,
      "loadReceiveTime": 65
    },
    {
      "id": 329,
      "type": 0.9509149873736418,
      "size": 85,
      "loadReceiveTime": 65
    }
  ],
  "66": [
    {
      "id": 330,
      "type": 0.7790942711638533,
      "size": 1885,
      "loadReceiveTime": 66
    },
    {
      "id": 331,
      "type": 0.0740308900898543,
      "size": 372,
      "loadReceiveTime": 66
    },
    {
      "id": 332,
      "type": 0.6707805982899007,
      "size": 1372,
      "loadReceiveTime": 66
    },
    {
      "id": 333,
      "type": 0.2040771904681642,
      "size": 473,
      "loadReceiveTime": 66
    },
    {
      "id": 334,
      "type": 0.16085823935361,
      "size": 1527,
      "loadReceiveTime": 66
    }
  ],
  "67": [
    {
      "id": 335,
      "type": 0.5280429946768972,
      "size": 1425,
      "loadReceiveTime": 67
    },
    {
      "id": 336,
      "type": 0.9816613903123834,
      "size": 697,
      "loadReceiveTime": 67
    },
    {
      "id": 337,
      "type": 0.8305316758314594,
      "size": 144,
      "loadReceiveTime": 67
    },
    {
      "id": 338,
      "type": 0.6918178344085291,
      "size": 1972,
      "loadReceiveTime": 67
    },
    {
      "id": 339,
      "type": 0.007935453001638004,
      "size": 2547,
      "loadReceiveTime": 67
    }
  ],
  "68": [
    {
      "id": 340,
      "type": 0.5676561734824357,
      "size": 476,
      "loadReceiveTime": 68
    },
    {
      "id": 341,
      "type": 0.2578910027412584,
      "size": 1249,
      "loadReceiveTime": 68
    },
    {
      "id": 342,
      "type": 0.20917772075345376,
      "size": 820,
      "loadReceiveTime": 68
    },
    {
      "id": 343,
      "type": 0.40541113179770005,
      "size": 1945,
      "loadReceiveTime": 68
    },
    {
      "id": 344,
      "type": 0.6745595926957659,
      "size": 398,
      "loadReceiveTime": 68
    }
  ],
  "69": [
    {
      "id": 345,
      "type": 0.44073151798107246,
      "size": 1187,
      "loadReceiveTime": 69
    },
    {
      "id": 346,
      "type": 0.9387637584190058,
      "size": 91,
      "loadReceiveTime": 69
    },
    {
      "id": 347,
      "type": 0.040150349388787365,
      "size": 13,
      "loadReceiveTime": 69
    },
    {
      "id": 348,
      "type": 0.9743833557674026,
      "size": 193,
      "loadReceiveTime": 69
    },
    {
      "id": 349,
      "type": 0.13393042306280067,
      "size": 1115,
      "loadReceiveTime": 69
    }
  ],
  "70": [
    {
      "id": 350,
      "type": 0.6827786199349246,
      "size": 327,
      "loadReceiveTime": 70
    },
    {
      "id": 351,
      "type": 0.5495452693701399,
      "size": 249,
      "loadReceiveTime": 70
    },
    {
      "id": 352,
      "type": 0.8893674322351852,
      "size": 471,
      "loadReceiveTime": 70
    },
    {
      "id": 353,
      "type": 0.18395259980179235,
      "size": 540,
      "loadReceiveTime": 70
    },
    {
      "id": 354,
      "type": 0.6372206730785843,
      "size": 3210,
      "loadReceiveTime": 70
    }
  ],
  "71": [
    {
      "id": 355,
      "type": 0.894992944713038,
      "size": 211,
      "loadReceiveTime": 71
    },
    {
      "id": 356,
      "type": 0.5174129630348043,
      "size": 1475,
      "loadReceiveTime": 71
    },
    {
      "id": 357,
      "type": 0.5555381697429573,
      "size": 673,
      "loadReceiveTime": 71
    },
    {
      "id": 358,
      "type": 0.3378763628380128,
      "size": 3571,
      "loadReceiveTime": 71
    },
    {
      "id": 359,
      "type": 0.9418077661295214,
      "size": 2214,
      "loadReceiveTime": 71
    }
  ],
  "72": [
    {
      "id": 360,
      "type": 0.415118997902592,
      "size": 1065,
      "loadReceiveTime": 72
    },
    {
      "id": 361,
      "type": 0.14012453891781163,
      "size": 1770,
      "loadReceiveTime": 72
    },
    {
      "id": 362,
      "type": 0.17402152954041616,
      "size": 1933,
      "loadReceiveTime": 72
    },
    {
      "id": 363,
      "type": 0.49194782350208843,
      "size": 663,
      "loadReceiveTime": 72
    },
    {
      "id": 364,
      "type": 0.23807816838687978,
      "size": 956,
      "loadReceiveTime": 72
    }
  ],
  "73": [
    {
      "id": 365,
      "type": 0.1615862551889904,
      "size": 196,
      "loadReceiveTime": 73
    },
    {
      "id": 366,
      "type": 0.09551996561994502,
      "size": 1420,
      "loadReceiveTime": 73
    },
    {
      "id": 367,
      "type": 0.24821985449857253,
      "size": 965,
      "loadReceiveTime": 73
    },
    {
      "id": 368,
      "type": 0.795919051499163,
      "size": 401,
      "loadReceiveTime": 73
    },
    {
      "id": 369,
      "type": 0.26325317806727866,
      "size": 1342,
      "loadReceiveTime": 73
    }
  ],
  "74": [
    {
      "id": 370,
      "type": 0.6396996615311745,
      "size": 345,
      "loadReceiveTime": 74
    },
    {
      "id": 371,
      "type": 0.06820453373342339,
      "size": 244,
      "loadReceiveTime": 74
    },
    {
      "id": 372,
      "type": 0.13422650886504894,
      "size": 2373,
      "loadReceiveTime": 74
    },
    {
      "id": 373,
      "type": 0.9631246056637579,
      "size": 1316,
      "loadReceiveTime": 74
    },
    {
      "id": 374,
      "type": 0.23368548555546287,
      "size": 1095,
      "loadReceiveTime": 74
    }
  ],
  "75": [
    {
      "id": 375,
      "type": 0.7924916034858407,
      "size": 2859,
      "loadReceiveTime": 75
    },
    {
      "id": 376,
      "type": 0.2577023089072352,
      "size": 1824,
      "loadReceiveTime": 75
    },
    {
      "id": 377,
      "type": 0.7856671473493815,
      "size": 484,
      "loadReceiveTime": 75
    },
    {
      "id": 378,
      "type": 0.5972944573471917,
      "size": 870,
      "loadReceiveTime": 75
    },
    {
      "id": 379,
      "type": 0.011850276382625369,
      "size": 255,
      "loadReceiveTime": 75
    }
  ],
  "76": [
    {
      "id": 380,
      "type": 0.1388095844835835,
      "size": 1976,
      "loadReceiveTime": 76
    },
    {
      "id": 381,
      "type": 0.26661433463108875,
      "size": 765,
      "loadReceiveTime": 76
    },
    {
      "id": 382,
      "type": 0.555914272367815,
      "size": 1928,
      "loadReceiveTime": 76
    },
    {
      "id": 383,
      "type": 0.1231556933343474,
      "size": 418,
      "loadReceiveTime": 76
    },
    {
      "id": 384,
      "type": 0.7673643034194144,
      "size": 310,
      "loadReceiveTime": 76
    }
  ],
  "77": [
    {
      "id": 385,
      "type": 0.01169475699062561,
      "size": 1035,
      "loadReceiveTime": 77
    },
    {
      "id": 386,
      "type": 0.6617220633950722,
      "size": 1564,
      "loadReceiveTime": 77
    },
    {
      "id": 387,
      "type": 0.9651766254345788,
      "size": 1391,
      "loadReceiveTime": 77
    },
    {
      "id": 388,
      "type": 0.3420425699504812,
      "size": 2583,
      "loadReceiveTime": 77
    },
    {
      "id": 389,
      "type": 0.009100632192611036,
      "size": 405,
      "loadReceiveTime": 77
    }
  ],
  "78": [
    {
      "id": 390,
      "type": 0.1866773650739777,
      "size": 407,
      "loadReceiveTime": 78
    },
    {
      "id": 391,
      "type": 0.5598681949813014,
      "size": 1142,
      "loadReceiveTime": 78
    },
    {
      "id": 392,
      "type": 0.12286159392187401,
      "size": 2436,
      "loadReceiveTime": 78
    },
    {
      "id": 393,
      "type": 0.8813546232420475,
      "size": 485,
      "loadReceiveTime": 78
    },
    {
      "id": 394,
      "type": 0.05413579336896501,
      "size": 585,
      "loadReceiveTime": 78
    }
  ],
  "79": [
    {
      "id": 395,
      "type": 0.6221208558962417,
      "size": 6645,
      "loadReceiveTime": 79
    },
    {
      "id": 396,
      "type": 0.7101868818615162,
      "size": 88,
      "loadReceiveTime": 79
    },
    {
      "id": 397,
      "type": 0.9832219859708538,
      "size": 1346,
      "loadReceiveTime": 79
    },
    {
      "id": 398,
      "type": 0.37253845536207697,
      "size": 77,
      "loadReceiveTime": 79
    },
    {
      "id": 399,
      "type": 0.23073466121422004,
      "size": 585,
      "loadReceiveTime": 79
    }
  ],
  "80": [
    {
      "id": 400,
      "type": 0.7831492426813638,
      "size": 1541,
      "loadReceiveTime": 80
    },
    {
      "id": 401,
      "type": 0.2059691745265133,
      "size": 402,
      "loadReceiveTime": 80
    },
    {
      "id": 402,
      "type": 0.6693320682374773,
      "size": 125,
      "loadReceiveTime": 80
    },
    {
      "id": 403,
      "type": 0.057014652287655565,
      "size": 964,
      "loadReceiveTime": 80
    },
    {
      "id": 404,
      "type": 0.7441830762022714,
      "size": 413,
      "loadReceiveTime": 80
    }
  ],
  "81": [
    {
      "id": 405,
      "type": 0.01432948236726772,
      "size": 458,
      "loadReceiveTime": 81
    },
    {
      "id": 406,
      "type": 0.699954549094238,
      "size": 986,
      "loadReceiveTime": 81
    },
    {
      "id": 407,
      "type": 0.4747882825627239,
      "size": 137,
      "loadReceiveTime": 81
    },
    {
      "id": 408,
      "type": 0.14961849756674628,
      "size": 815,
      "loadReceiveTime": 81
    },
    {
      "id": 409,
      "type": 0.8852190661041621,
      "size": 2217,
      "loadReceiveTime": 81
    }
  ],
  "82": [
    {
      "id": 410,
      "type": 0.045918548627357,
      "size": 937,
      "loadReceiveTime": 82
    },
    {
      "id": 411,
      "type": 0.9768009582523549,
      "size": 4349,
      "loadReceiveTime": 82
    },
    {
      "id": 412,
      "type": 0.04813110717231606,
      "size": 890,
      "loadReceiveTime": 82
    },
    {
      "id": 413,
      "type": 0.1883333653296968,
      "size": 113,
      "loadReceiveTime": 82
    },
    {
      "id": 414,
      "type": 0.47361544023816826,
      "size": 1034,
      "loadReceiveTime": 82
    }
  ],
  "83": [
    {
      "id": 415,
      "type": 0.5967216258864874,
      "size": 409,
      "loadReceiveTime": 83
    },
    {
      "id": 416,
      "type": 0.3958549766640074,
      "size": 1104,
      "loadReceiveTime": 83
    },
    {
      "id": 417,
      "type": 0.38275272976912333,
      "size": 7,
      "loadReceiveTime": 83
    },
    {
      "id": 418,
      "type": 0.5453382205189292,
      "size": 844,
      "loadReceiveTime": 83
    },
    {
      "id": 419,
      "type": 0.084541797528223,
      "size": 1464,
      "loadReceiveTime": 83
    }
  ],
  "84": [
    {
      "id": 420,
      "type": 0.4270602902810716,
      "size": 122,
      "loadReceiveTime": 84
    },
    {
      "id": 421,
      "type": 0.9279846123194144,
      "size": 876,
      "loadReceiveTime": 84
    },
    {
      "id": 422,
      "type": 0.4786467525616682,
      "size": 881,
      "loadReceiveTime": 84
    },
    {
      "id": 423,
      "type": 0.16714402931627115,
      "size": 892,
      "loadReceiveTime": 84
    },
    {
      "id": 424,
      "type": 0.5881873102957595,
      "size": 1027,
      "loadReceiveTime": 84
    }
  ],
  "85": [
    {
      "id": 425,
      "type": 0.19151448204613697,
      "size": 268,
      "loadReceiveTime": 85
    },
    {
      "id": 426,
      "type": 0.550005112222234,
      "size": 842,
      "loadReceiveTime": 85
    },
    {
      "id": 427,
      "type": 0.7111392076027667,
      "size": 1366,
      "loadReceiveTime": 85
    },
    {
      "id": 428,
      "type": 0.15323318446881684,
      "size": 201,
      "loadReceiveTime": 85
    },
    {
      "id": 429,
      "type": 0.6019173912363318,
      "size": 3157,
      "loadReceiveTime": 85
    }
  ],
  "86": [
    {
      "id": 430,
      "type": 0.13392745616395518,
      "size": 1628,
      "loadReceiveTime": 86
    },
    {
      "id": 431,
      "type": 0.9026637361346206,
      "size": 1347,
      "loadReceiveTime": 86
    },
    {
      "id": 432,
      "type": 0.6489998565399584,
      "size": 508,
      "loadReceiveTime": 86
    },
    {
      "id": 433,
      "type": 0.270592930009272,
      "size": 236,
      "loadReceiveTime": 86
    },
    {
      "id": 434,
      "type": 0.09373580879433874,
      "size": 3693,
      "loadReceiveTime": 86
    }
  ],
  "87": [
    {
      "id": 435,
      "type": 0.9104134840797351,
      "size": 686,
      "loadReceiveTime": 87
    },
    {
      "id": 436,
      "type": 0.29931297716843175,
      "size": 1606,
      "loadReceiveTime": 87
    },
    {
      "id": 437,
      "type": 0.3642055954330554,
      "size": 1224,
      "loadReceiveTime": 87
    },
    {
      "id": 438,
      "type": 0.3508715966925553,
      "size": 1040,
      "loadReceiveTime": 87
    },
    {
      "id": 439,
      "type": 0.5220074063625901,
      "size": 916,
      "loadReceiveTime": 87
    }
  ],
  "89": [
    {
      "id": 440,
      "type": 0.44851623234620575,
      "size": 2551,
      "loadReceiveTime": 89
    },
    {
      "id": 441,
      "type": 0.9925932928595813,
      "size": 3077,
      "loadReceiveTime": 89
    },
    {
      "id": 442,
      "type": 0.7264858731974866,
      "size": 1881,
      "loadReceiveTime": 89
    },
    {
      "id": 443,
      "type": 0.11388282234688818,
      "size": 285,
      "loadReceiveTime": 89
    },
    {
      "id": 444,
      "type": 0.7435908441079597,
      "size": 735,
      "loadReceiveTime": 89
    }
  ],
  "90": [
    {
      "id": 445,
      "type": 0.9063453518507048,
      "size": 367,
      "loadReceiveTime": 90
    },
    {
      "id": 446,
      "type": 0.390480212176745,
      "size": 907,
      "loadReceiveTime": 90
    },
    {
      "id": 447,
      "type": 0.7470913178723955,
      "size": 840,
      "loadReceiveTime": 90
    },
    {
      "id": 448,
      "type": 0.5901590937922259,
      "size": 1760,
      "loadReceiveTime": 90
    },
    {
      "id": 449,
      "type": 0.527851663276292,
      "size": 2266,
      "loadReceiveTime": 90
    }
  ],
  "91": [
    {
      "id": 450,
      "type": 0.10623534679261448,
      "size": 1731,
      "loadReceiveTime": 91
    },
    {
      "id": 451,
      "type": 0.08343886437439108,
      "size": 2882,
      "loadReceiveTime": 91
    },
    {
      "id": 452,
      "type": 0.42498032871941005,
      "size": 1390,
      "loadReceiveTime": 91
    },
    {
      "id": 453,
      "type": 0.8676231687623819,
      "size": 419,
      "loadReceiveTime": 91
    },
    {
      "id": 454,
      "type": 0.23434788415295138,
      "size": 2168,
      "loadReceiveTime": 91
    }
  ],
  "92": [
    {
      "id": 455,
      "type": 0.22601565646752064,
      "size": 1996,
      "loadReceiveTime": 92
    },
    {
      "id": 456,
      "type": 0.7106001374374811,
      "size": 2409,
      "loadReceiveTime": 92
    },
    {
      "id": 457,
      "type": 0.3995625872561801,
      "size": 976,
      "loadReceiveTime": 92
    },
    {
      "id": 458,
      "type": 0.647408778831313,
      "size": 3143,
      "loadReceiveTime": 92
    },
    {
      "id": 459,
      "type": 0.6833451302281488,
      "size": 599,
      "loadReceiveTime": 92
    }
  ],
  "93": [
    {
      "id": 460,
      "type": 0.3394629942129037,
      "size": 749,
      "loadReceiveTime": 93
    },
    {
      "id": 461,
      "type": 0.9579613714861996,
      "size": 593,
      "loadReceiveTime": 93
    },
    {
      "id": 462,
      "type": 0.7707173109921841,
      "size": 2035,
      "loadReceiveTime": 93
    },
    {
      "id": 463,
      "type": 0.713220301500407,
      "size": 500,
      "loadReceiveTime": 93
    },
    {
      "id": 464,
      "type": 0.4892722436214434,
      "size": 1663,
      "loadReceiveTime": 93
    }
  ],
  "94": [
    {
      "id": 465,
      "type": 0.0018420933641416504,
      "size": 1316,
      "loadReceiveTime": 94
    },
    {
      "id": 466,
      "type": 0.7353366078929495,
      "size": 297,
      "loadReceiveTime": 94
    },
    {
      "id": 467,
      "type": 0.9330095437441379,
      "size": 4819,
      "loadReceiveTime": 94
    },
    {
      "id": 468,
      "type": 0.7666102157200771,
      "size": 1072,
      "loadReceiveTime": 94
    },
    {
      "id": 469,
      "type": 0.31361788269794033,
      "size": 215,
      "loadReceiveTime": 94
    }
  ],
  "95": [
    {
      "id": 470,
      "type": 0.5592516860454264,
      "size": 1219,
      "loadReceiveTime": 95
    },
    {
      "id": 471,
      "type": 0.10385160659918302,
      "size": 435,
      "loadReceiveTime": 95
    },
    {
      "id": 472,
      "type": 0.26408241230768636,
      "size": 1351,
      "loadReceiveTime": 95
    },
    {
      "id": 473,
      "type": 0.3806111154821632,
      "size": 437,
      "loadReceiveTime": 95
    },
    {
      "id": 474,
      "type": 0.8177217643092982,
      "size": 5836,
      "loadReceiveTime": 95
    }
  ],
  "96": [
    {
      "id": 475,
      "type": 0.498170740265242,
      "size": 1177,
      "loadReceiveTime": 96
    },
    {
      "id": 476,
      "type": 0.86989222567261,
      "size": 455,
      "loadReceiveTime": 96
    },
    {
      "id": 477,
      "type": 0.7336875325636161,
      "size": 127,
      "loadReceiveTime": 96
    },
    {
      "id": 478,
      "type": 0.18130139030522208,
      "size": 218,
      "loadReceiveTime": 96
    },
    {
      "id": 479,
      "type": 0.021162100517566618,
      "size": 304,
      "loadReceiveTime": 96
    }
  ],
  "97": [
    {
      "id": 480,
      "type": 0.08844623705236176,
      "size": 925,
      "loadReceiveTime": 97
    },
    {
      "id": 481,
      "type": 0.06745650185649632,
      "size": 132,
      "loadReceiveTime": 97
    },
    {
      "id": 482,
      "type": 0.7904209856528277,
      "size": 152,
      "loadReceiveTime": 97
    },
    {
      "id": 483,
      "type": 0.9131180284887537,
      "size": 3494,
      "loadReceiveTime": 97
    },
    {
      "id": 484,
      "type": 0.4969873859692817,
      "size": 139,
      "loadReceiveTime": 97
    }
  ],
  "98": [
    {
      "id": 485,
      "type": 0.29312621047889675,
      "size": 3381,
      "loadReceiveTime": 98
    },
    {
      "id": 486,
      "type": 0.036591504728118895,
      "size": 2149,
      "loadReceiveTime": 98
    },
    {
      "id": 487,
      "type": 0.09923104718344922,
      "size": 894,
      "loadReceiveTime": 98
    },
    {
      "id": 488,
      "type": 0.7567654631608505,
      "size": 119,
      "loadReceiveTime": 98
    },
    {
      "id": 489,
      "type": 0.5721186747148852,
      "size": 761,
      "loadReceiveTime": 98
    }
  ],
  "99": [
    {
      "id": 490,
      "type": 0.15744294614335974,
      "size": 2481,
      "loadReceiveTime": 99
    },
    {
      "id": 491,
      "type": 0.2562087660957879,
      "size": 487,
      "loadReceiveTime": 99
    },
    {
      "id": 492,
      "type": 0.3703454989409425,
      "size": 212,
      "loadReceiveTime": 99
    },
    {
      "id": 493,
      "type": 0.8732218448193094,
      "size": 813,
      "loadReceiveTime": 99
    },
    {
      "id": 494,
      "type": 0.36856196779958417,
      "size": 813,
      "loadReceiveTime": 99
    }
  ],
  "100": [
    {
      "id": 495,
      "type": 0.35110561476915114,
      "size": 509,
      "loadReceiveTime": 100
    },
    {
      "id": 496,
      "type": 0.6142881329840972,
      "size": 2731,
      "loadReceiveTime": 100
    },
    {
      "id": 497,
      "type": 0.25146621687514026,
      "size": 1348,
      "loadReceiveTime": 100
    },
    {
      "id": 498,
      "type": 0.2665390489171531,
      "size": 936,
      "loadReceiveTime": 100
    },
    {
      "id": 499,
      "type": 0.12536110184072613,
      "size": 941,
      "loadReceiveTime": 100
    }
  ]
}